orange3biosci/__init__.py
orange3biosci/icons/ElementsPairing.svg
orange3biosci/icons/ListSplitter.svg
orange3biosci/icons/Pivot-alternative.svg
orange3biosci/icons/Transpose-string.svg
orange3biosci/icons/arrow.svg
orange3biosci/icons/biosci-category-icon.svg
orange3biosci/icons/preprocessing-icon.svg
orange3biosci/icons/soft-extractor-icon.svg
orange3biosci/widgets/__init__.py
orange3biosci/widgets/elements_pairing.py
orange3biosci/widgets/geo_preprocessor.py
orange3biosci/widgets/geo_soft_extractor.py
orange3biosci/widgets/list_splitter.py
orange3biosci/widgets/pivot_custom.py
orange3biosci/widgets/simple_transpose.py
orange_biosci-0.6.2.dist-info/licenses/LICENSE
orange_biosci-0.6.2.dist-info/METADATA
orange_biosci-0.6.2.dist-info/WHEEL
orange_biosci-0.6.2.dist-info/entry_points.txt
orange_biosci-0.6.2.dist-info/top_level.txt
orange_biosci-0.6.2.dist-info/RECORD
