Metadata-Version: 2.4
Name: orange-biosci
Version: 0.6.2
Summary: Custom Orange Bio Sci Widgets
Home-page: https://github.com/santanche/orange-biosci
Author: André Santanchè
License:                   GNU LESSER GENERAL PUBLIC LICENSE
Project-URL: Homepage, https://github.com/santanche/orange-biosci
Classifier: Development Status :: 4 - Beta
Classifier: Intended Audience :: Science/Research
Classifier: License :: OSI Approved :: GNU General Public License v3 or later (GPLv3+)
Classifier: Programming Language :: Python :: 3
Classifier: Topic :: Scientific/Engineering :: Visualization
Classifier: Topic :: Scientific/Engineering :: Information Analysis
License-File: LICENSE
Dynamic: home-page
Dynamic: license-file
